simple_sqs_client/__init__.py
simple_sqs_client/builder.py
simple_sqs_client/client.py
simple_sqs_client/setup.py
simple_sqs_client/test_client.py
simple_sqs_client-0.9.6.dist-info/LICENSE
simple_sqs_client-0.9.6.dist-info/METADATA
simple_sqs_client-0.9.6.dist-info/WHEEL
simple_sqs_client-0.9.6.dist-info/top_level.txt
simple_sqs_client-0.9.6.dist-info/RECORD
