Metadata-Version: 2.1
Name: simple-sqs-client
Version: 0.9.6
Summary: Very simple SQS Client
Home-page: https://github.com/a-laurowski/simple_sqs_client
Author: Aleksander Laurowski
Author-email: aleksander.laurowski191@gmail.com
Project-URL: Documentation, https://github.com/a-laurowski/simple_sqs_client/blob/main/README.md
Project-URL: Bug Reports, https://github.com/a-laurowski/simple_sqs_client/issues
Project-URL: Source Code, https://github.com/a-laurowski/simple_sqs_client
Keywords: simple_sqs_client
Classifier: Development Status :: 5 - Production/Stable
Classifier: Intended Audience :: Developers
Classifier: Topic :: Software Development :: Build Tools
Classifier: Programming Language :: Python :: 3
Classifier: Programming Language :: Python :: 3.6
Classifier: Programming Language :: Python :: 3.7
Classifier: Programming Language :: Python :: 3.8
Classifier: Programming Language :: Python :: 3.9
Classifier: Programming Language :: Python :: 3 :: Only
Classifier: License :: OSI Approved :: MIT License
Classifier: Operating System :: OS Independent
Requires-Python: >=3.6
License-File: LICENSE
Provides-Extra: dev
Requires-Dist: check-manifest ; extra == 'dev'
